binance_candle_fetcher/__init__.py
binance_candle_fetcher/fetch_candles.py
candles_fetcher-0.1.2.dist-info/METADATA
candles_fetcher-0.1.2.dist-info/WHEEL
candles_fetcher-0.1.2.dist-info/top_level.txt
candles_fetcher-0.1.2.dist-info/RECORD
