Metadata-Version: 2.2
Name: candles_fetcher
Version: 0.1.2
Summary: A simple package to fetch candlestick data.
Home-page: https://github.com/yourusername/candles-fetcher
Author: Wynne
Author-email: wynne1999.work@example.com
Classifier: Programming Language :: Python :: 3
Classifier: License :: OSI Approved :: MIT License
Classifier: Operating System :: OS Independent
Requires-Python: >=3.7
Requires-Dist: ccxt
Requires-Dist: pandas
Requires-Dist: asyncio
Dynamic: author
Dynamic: author-email
Dynamic: classifier
Dynamic: description
Dynamic: description-content-type
Dynamic: home-page
Dynamic: requires-dist
Dynamic: requires-python
Dynamic: summary
